sparqlquery/__init__.py
sparqlquery/exceptions.py
sparqlquery/mapper/__init__.py
sparqlquery/mapper/declarative.py
sparqlquery/mapper/properties.py
sparqlquery/mapper/query.py
sparqlquery/mapper/session.py
sparqlquery/sparql/__init__.py
sparqlquery/sparql/compiler.py
sparqlquery/sparql/expressions.py
sparqlquery/sparql/helpers.py
sparqlquery/sparql/operators.py
sparqlquery/sparql/patterns.py
sparqlquery/sparql/query.py
sparqlquery/sparql/queryforms.py
sparqlquery/sparql/util.py
sparqlquery-0.2.1.dist-info/DESCRIPTION.rst
sparqlquery-0.2.1.dist-info/METADATA
sparqlquery-0.2.1.dist-info/metadata.json
sparqlquery-0.2.1.dist-info/RECORD
sparqlquery-0.2.1.dist-info/top_level.txt
sparqlquery-0.2.1.dist-info/WHEEL
tests/__init__.py
tests/helpers.py
tests/run_all.py
tests/test_compiler.py
tests/test_expressions.py
tests/test_mapper.py
tests/test_modifiers.py
tests/test_operators.py
tests/test_patterns.py
tests/test_select.py
