Metadata-Version: 2.0
Name: sparqlquery
Version: 0.2.1
Summary: SPARQL query builder, fork of sparqlquery
Home-page: https://github.com/pudo/sparqlquery
Author: Brian Beck, Friedrich Lindenberg
Author-email: friedrich@pudo.org
License: MIT
Keywords: rdf rdflib sparql orm
Platform: UNKNOWN
Classifier: Development Status :: 3 - Alpha
Classifier: Intended Audience :: Developers
Classifier: License :: OSI Approved :: MIT License
Classifier: Operating System :: OS Independent
Classifier: Programming Language :: Python :: 2.6
Classifier: Programming Language :: Python :: 2.7
Classifier: Programming Language :: Python :: 3.3
Classifier: Programming Language :: Python :: 3.4
Requires-Dist: rdflib (>=4.2.1)
